sangTools/__init__.py
sangTools/data_op.py
sangTools/roman.py
sangTools/flashtext/__init__.py
sangTools/flashtext/keyword.py
sangTools-0.0.2.dist-info/LICENSE
sangTools-0.0.2.dist-info/METADATA
sangTools-0.0.2.dist-info/WHEEL
sangTools-0.0.2.dist-info/top_level.txt
sangTools-0.0.2.dist-info/RECORD
