Metadata-Version: 2.1
Name: sangTools
Version: 0.0.2
Summary: sangtools
Home-page: https://github.com/pzydzh/sangTools
Author: sangplus
Author-email: jiajun_sang@outlook.com
License: MIT
Platform: UNKNOWN
License-File: LICENSE
